PyPrint-0.2.6.dist-info/DESCRIPTION.rst
PyPrint-0.2.6.dist-info/METADATA
PyPrint-0.2.6.dist-info/RECORD
PyPrint-0.2.6.dist-info/WHEEL
PyPrint-0.2.6.dist-info/metadata.json
PyPrint-0.2.6.dist-info/top_level.txt
pyprint/ClosableObject.py
pyprint/ColorPrinter.py
pyprint/ConsolePrinter.py
pyprint/Constants.py
pyprint/ContextManagers.py
pyprint/EspeakPrinter.py
pyprint/FilePrinter.py
pyprint/NullPrinter.py
pyprint/Printer.py
pyprint/StringPrinter.py
pyprint/VERSION
pyprint/__init__.py
