Metadata-Version: 1.0
Name: PyPrint
Version: 0.2.6
Summary: A library providing printing facilities for python applications.
Home-page: UNKNOWN
Author: Lasse Schuirmann, Mischa Krüger
Author-email: lasse.schuirmann@gmail.com, makman@alice.de
License: GPL v3
Platform: any
